odoo/addons/account_move_post_block/README.rst
odoo/addons/account_move_post_block/__init__.py
odoo/addons/account_move_post_block/__manifest__.py
odoo/addons/account_move_post_block/data/account_exception_data.xml
odoo/addons/account_move_post_block/i18n/account_move_post_block.pot
odoo/addons/account_move_post_block/models/__init__.py
odoo/addons/account_move_post_block/models/account_move.py
odoo/addons/account_move_post_block/models/account_post_block_reason.py
odoo/addons/account_move_post_block/readme/CONFIGURE.rst
odoo/addons/account_move_post_block/readme/CONTRIBUTORS.rst
odoo/addons/account_move_post_block/readme/DESCRIPTION.rst
odoo/addons/account_move_post_block/readme/USAGE.rst
odoo/addons/account_move_post_block/security/account_move_post_block_security.xml
odoo/addons/account_move_post_block/security/ir.model.access.csv
odoo/addons/account_move_post_block/static/description/icon.png
odoo/addons/account_move_post_block/static/description/index.html
odoo/addons/account_move_post_block/tests/__init__.py
odoo/addons/account_move_post_block/tests/test_account_move_post_block.py
odoo/addons/account_move_post_block/tests/test_am_post_block_reason.py
odoo/addons/account_move_post_block/views/account_move_view.xml
odoo/addons/account_move_post_block/views/account_post_block_reason_view.xml
odoo/addons/account_move_post_block/wizard/__init__.py
odoo/addons/account_move_post_block/wizard/account_exception_confirm.py
odoo13_addon_account_move_post_block-13.0.1.0.2.dist-info/METADATA
odoo13_addon_account_move_post_block-13.0.1.0.2.dist-info/WHEEL
odoo13_addon_account_move_post_block-13.0.1.0.2.dist-info/top_level.txt
odoo13_addon_account_move_post_block-13.0.1.0.2.dist-info/RECORD
